[
  {
    "Type": "BlueprintGeneratedClass",
    "Name": "DmgTypeInstant_Fall_C",
    "Super": "DmgType_Instant_C",
    "Class": "UScriptClass'BlueprintGeneratedClass'",
    "Next": null,
    "SuperStruct": {
      "ObjectName": "BlueprintGeneratedClass'DmgType_Instant_C'",
      "ObjectPath": "TslGame/Content/Blueprints/Damage_Type/DmgType_Instant.0"
    },
    "ClassFlags": 327696,
    "ClassWithin": {
      "ObjectName": "Class'Object'",
      "ObjectPath": "/Script/CoreUObject"
    },
    "ClassConfigName": "Engine",
    "bCooked": true,
    "ClassDefaultObject": {
      "ObjectName": "DmgTypeInstant_Fall_C'Default__DmgTypeInstant_Fall_C'",
      "ObjectPath": "TslGame/Content/Blueprints/Damage_Type/DmgTypeInstant_Fall.1"
    }
  },
  {
    "Type": "DmgTypeInstant_Fall_C",
    "Name": "Default__DmgTypeInstant_Fall_C",
    "Template": "Default__DmgType_Instant_C",
    "Class": "BlueprintGeneratedClass'TslGame/Content/Blueprints/Damage_Type/DmgTypeInstant_Fall.DmgTypeInstant_Fall_C'",
    "Properties": {
      "DamageTypeCategory": "EDamageTypeCategory::Damage_Instant_Fall",
      "bFallDamage": true
    }
  }
]