[
  {
    "Type": "BlueprintGeneratedClass",
    "Name": "DmgTypeFire_JerryCan_C",
    "Class": "UScriptClass'BlueprintGeneratedClass'",
    "Next": null,
    "SuperStruct": {
      "ObjectName": "Class'TslDamageType'",
      "ObjectPath": "/Script/TslGame"
    },
    "ClassFlags": 327696,
    "ClassWithin": {
      "ObjectName": "Class'Object'",
      "ObjectPath": "/Script/CoreUObject"
    },
    "ClassConfigName": "Engine",
    "bCooked": true,
    "ClassDefaultObject": {
      "ObjectName": "DmgTypeFire_JerryCan_C'Default__DmgTypeFire_JerryCan_C'",
      "ObjectPath": "TslGame/Content/Blueprints/Damage_Type/DmgTypeFire_JerryCan.1"
    }
  },
  {
    "Type": "DmgTypeFire_JerryCan_C",
    "Name": "Default__DmgTypeFire_JerryCan_C",
    "Class": "BlueprintGeneratedClass'TslGame/Content/Blueprints/Damage_Type/DmgTypeFire_JerryCan.DmgTypeFire_JerryCan_C'",
    "Properties": {
      "DamageTypeCategory": "EDamageTypeCategory::Damage_Explosion_JerryCan",
      "HitForceFeedback": {
        "ObjectName": "TslForceFeedbackEffect'TslFFE_Damaged'",
        "ObjectPath": "TslGame/Content/Effects/ForceFeedback/TslFFE_Damaged.0"
      },
      "KilledForceFeedback": {
        "ObjectName": "TslForceFeedbackEffect'TslFFE_Killed'",
        "ObjectPath": "TslGame/Content/Effects/ForceFeedback/TslFFE_Killed.0"
      },
      "OverrideDamageCauserName": "JerrycanFire",
      "DamageImpulse": 0.0
    }
  }
]