[
  {
    "Type": "CurveFloat",
    "Name": "C4DistanceCurveVertical",
    "Class": "UScriptClass'CurveFloat'",
    "Properties": {
      "FloatCurve": {
        "Keys": [
          {
            "InterpMode": "RCIM_Linear",
            "TangentMode": "RCTM_Auto",
            "TangentWeightMode": "RCTWM_WeightedNone",
            "Time": 0.0,
            "Value": 0.14,
            "ArriveTangent": 0.0,
            "ArriveTangentWeight": 0.0,
            "LeaveTangent": 0.0,
            "LeaveTangentWeight": 0.0
          },
          {
            "InterpMode": "RCIM_Linear",
            "TangentMode": "RCTM_Auto",
            "TangentWeightMode": "RCTWM_WeightedNone",
            "Time": 0.1,
            "Value": 0.13,
            "ArriveTangent": 0.0,
            "ArriveTangentWeight": 0.0,
            "LeaveTangent": 0.0,
            "LeaveTangentWeight": 0.0
          },
          {
            "InterpMode": "RCIM_Linear",
            "TangentMode": "RCTM_Auto",
            "TangentWeightMode": "RCTWM_WeightedNone",
            "Time": 0.35,
            "Value": 0.11,
            "ArriveTangent": -0.5726867,
            "ArriveTangentWeight": 0.0,
            "LeaveTangent": -0.57269114,
            "LeaveTangentWeight": 0.0
          },
          {
            "InterpMode": "RCIM_Linear",
            "TangentMode": "RCTM_Auto",
            "TangentWeightMode": "RCTWM_WeightedNone",
            "Time": 0.5,
            "Value": 0.075,
            "ArriveTangent": 0.0,
            "ArriveTangentWeight": 0.0,
            "LeaveTangent": 0.0,
            "LeaveTangentWeight": 0.0
          },
          {
            "InterpMode": "RCIM_Linear",
            "TangentMode": "RCTM_Auto",
            "TangentWeightMode": "RCTWM_WeightedNone",
            "Time": 0.75,
            "Value": 0.03,
            "ArriveTangent": 0.0,
            "ArriveTangentWeight": 0.0,
            "LeaveTangent": 0.0,
            "LeaveTangentWeight": 0.0
          },
          {
            "InterpMode": "RCIM_Linear",
            "TangentMode": "RCTM_Auto",
            "TangentWeightMode": "RCTWM_WeightedNone",
            "Time": 0.999,
            "Value": 0.01,
            "ArriveTangent": 0.0,
            "ArriveTangentWeight": 0.0,
            "LeaveTangent": 0.0,
            "LeaveTangentWeight": 0.0
          }
        ]
      }
    }
  }
]