[
  {
    "Type": "BodySetup",
    "Name": "BodySetup_2",
    "Outer": "Grass_type02_3",
    "Class": "UScriptClass'BodySetup'",
    "Properties": {
      "AggGeom": {
        "ConvexElems": [
          {
            "VertexData": [
              {
                "X": 235.5456,
                "Y": 72.82938,
                "Z": 22.295547
              },
              {
                "X": 235.5456,
                "Y": -94.32948,
                "Z": 22.295546
              },
              {
                "X": 235.5456,
                "Y": -94.329475,
                "Z": 95.57942
              },
              {
                "X": 235.5456,
                "Y": 72.82942,
                "Z": 95.57942
              },
              {
                "X": -264.22144,
                "Y": -46.778595,
                "Z": 2.5964706
              },
              {
                "X": -264.22144,
                "Y": 127.528534,
                "Z": 2.5964754
              },
              {
                "X": -264.22144,
                "Y": 127.52855,
                "Z": 125.90348
              },
              {
                "X": -264.22144,
                "Y": -46.77858,
                "Z": 125.90349
              },
              {
                "X": -172.38132,
                "Y": 219.36867,
                "Z": 13.743653
              },
              {
                "X": 89.00632,
                "Y": 219.36867,
                "Z": 13.743655
              },
              {
                "X": 89.00633,
                "Y": 219.36867,
                "Z": 93.63133
              },
              {
                "X": -172.38133,
                "Y": 219.36867,
                "Z": 93.63133
              },
              {
                "X": 110.06189,
                "Y": -219.8132,
                "Z": -3.0617898
              },
              {
                "X": -91.186844,
                "Y": -219.8132,
                "Z": -3.0618005
              },
              {
                "X": -91.18678,
                "Y": -219.8132,
                "Z": 144.18675
              },
              {
                "X": 110.06186,
                "Y": -219.8132,
                "Z": 144.18677
              },
              {
                "X": -208.22025,
                "Y": -102.77977,
                "Z": 181.9047
              },
              {
                "X": -208.22025,
                "Y": 131.0953,
                "Z": 181.9047
              },
              {
                "X": 149.2203,
                "Y": 131.0953,
                "Z": 181.9047
              },
              {
                "X": 149.22034,
                "Y": -180.65475,
                "Z": 181.9047
              },
              {
                "X": 147.77977,
                "Y": -182.0953,
                "Z": 181.9047
              },
              {
                "X": -128.90472,
                "Y": -182.09528,
                "Z": 181.9047
              },
              {
                "X": -213.39572,
                "Y": -97.60431,
                "Z": -48.229248
              },
              {
                "X": -136.35425,
                "Y": -174.64574,
                "Z": -48.229248
              },
              {
                "X": 155.22934,
                "Y": -174.6457,
                "Z": -48.229248
              },
              {
                "X": 165.02078,
                "Y": -164.85428,
                "Z": -48.229248
              },
              {
                "X": 165.0208,
                "Y": 143.3542,
                "Z": -48.229248
              },
              {
                "X": 150.9792,
                "Y": 157.3958,
                "Z": -48.229248
              },
              {
                "X": -213.39572,
                "Y": 157.39575,
                "Z": -48.229248
              },
              {
                "X": 163.25,
                "Y": 145.125,
                "Z": 167.875
              },
              {
                "X": -234.43745,
                "Y": 157.31252,
                "Z": 155.68748
              },
              {
                "X": -223.87498,
                "Y": 167.87502,
                "Z": -37.749985
              }
            ],
            "ElemBox": {
              "Min": {
                "X": -264.22144,
                "Y": -219.8132,
                "Z": -48.229248
              },
              "Max": {
                "X": 235.5456,
                "Y": 219.36867,
                "Z": 181.9047
              },
              "IsValid": 1
            },
            "Transform": {
              "Rotation": {
                "X": 0.0,
                "Y": 0.0,
                "Z": 0.0,
                "W": 1.0,
                "IsNormalized": true,
                "Size": 1.0,
                "SizeSquared": 1.0
              },
              "Translation": {
                "X": 0.0,
                "Y": 0.0,
                "Z": 0.0
              },
              "Scale3D": {
                "X": 1.0,
                "Y": 1.0,
                "Z": 1.0
              }
            }
          }
        ]
      },
      "DefaultInstance": {
        "CollisionProfileName": "NoCollision",
        "CollisionResponses": {
          "ResponseArray": [
            {
              "Channel": "Visibility",
              "Response": "ECR_Ignore"
            },
            {
              "Channel": "Camera",
              "Response": "ECR_Ignore"
            },
            {
              "Channel": "OverlapObject",
              "Response": "ECR_Ignore"
            }
          ]
        },
        "CollisionEnabled": "ECollisionEnabled::NoCollision",
        "ObjectType": "ECC_WorldStatic"
      }
    },
    "BodySetupGuid": "DE240D0B4A7341F8459902B708383D6D",
    "CookedFormatData": {
      "PhysXPC": {
        "BulkDataFlags": "BULKDATA_SingleUse | BULKDATA_ForceInlinePayload",
        "ElementCount": 2403,
        "SizeOnDisk": 2403,
        "OffsetInFile": "0x4AAC"
      }
    }
  },
  {
    "Type": "StaticMesh",
    "Name": "Grass_type02_3",
    "Class": "UScriptClass'StaticMesh'",
    "Properties": {
      "StaticMaterials": [
        {
          "MaterialSlotName": "grass_1_LOD0_Inst",
          "UVChannelData": {
            "bInitialized": true,
            "bOverrideDensities": false,
            "LocalUVDensities": 186.06319,
            "LocalUVDensities": 37759.742,
            "LocalUVDensities": 1246.5029,
            "LocalUVDensities": 1049.363
          }
        }
      ],
      "LightmapUVDensity": 1049.363,
      "LightMapCoordinateIndex": 3,
      "ExtendedBounds": {
        "Origin": {
          "X": -14.337906,
          "Y": -0.22225952,
          "Z": 66.837715
        },
        "BoxExtent": {
          "X": 249.78352,
          "Y": 219.49094,
          "Z": 114.966965
        },
        "SphereRadius": 268.68152
      }
    },
    "BodySetup": {
      "ObjectName": "BodySetup'Grass_type02_3:BodySetup_2'",
      "ObjectPath": "TslGame/Content/Maps/tiger/Art/LandscapeMaterial/Grass/NW_Grass_Type02/Grass_type02_3.0"
    },
    "NavCollision": null,
    "LightingGuid": "2DA21C45-4C27395F-A726C9B9-69A2DFAA",
    "RenderData": {
      "LODs": [
        {
          "Sections": [
            {
              "MaterialIndex": 0,
              "FirstIndex": 0,
              "NumTriangles": 52,
              "MinVertexIndex": 0,
              "MaxVertexIndex": 103,
              "bEnableCollision": false,
              "bCastShadow": true,
              "bForceOpaque": false,
              "bVisibleInRayTracing": true
            }
          ],
          "MaxDeviation": 0.0,
          "PositionVertexBuffer": {
            "Stride": 12,
            "NumVertices": 104
          },
          "VertexBuffer": {
            "NumTexCoords": 4,
            "NumVertices": 104,
            "Strides": 24,
            "UseHighPrecisionTangentBasis": false,
            "UseFullPrecisionUVs": false
          },
          "ColorVertexBuffer": {
            "Stride": 0,
            "NumVertices": 0
          }
        },
        {
          "Sections": [
            {
              "MaterialIndex": 0,
              "FirstIndex": 0,
              "NumTriangles": 26,
              "MinVertexIndex": 0,
              "MaxVertexIndex": 63,
              "bEnableCollision": false,
              "bCastShadow": true,
              "bForceOpaque": false,
              "bVisibleInRayTracing": true
            }
          ],
          "MaxDeviation": 0.0,
          "PositionVertexBuffer": {
            "Stride": 12,
            "NumVertices": 64
          },
          "VertexBuffer": {
            "NumTexCoords": 4,
            "NumVertices": 64,
            "Strides": 24,
            "UseHighPrecisionTangentBasis": false,
            "UseFullPrecisionUVs": false
          },
          "ColorVertexBuffer": {
            "Stride": 0,
            "NumVertices": 0
          }
        },
        {
          "Sections": [
            {
              "MaterialIndex": 0,
              "FirstIndex": 0,
              "NumTriangles": 13,
              "MinVertexIndex": 0,
              "MaxVertexIndex": 30,
              "bEnableCollision": false,
              "bCastShadow": true,
              "bForceOpaque": false,
              "bVisibleInRayTracing": true
            }
          ],
          "MaxDeviation": 0.0,
          "PositionVertexBuffer": {
            "Stride": 12,
            "NumVertices": 31
          },
          "VertexBuffer": {
            "NumTexCoords": 4,
            "NumVertices": 31,
            "Strides": 24,
            "UseHighPrecisionTangentBasis": false,
            "UseFullPrecisionUVs": false
          },
          "ColorVertexBuffer": {
            "Stride": 0,
            "NumVertices": 0
          }
        }
      ],
      "Bounds": {
        "Origin": {
          "X": -14.337906,
          "Y": -0.22225952,
          "Z": 66.837715
        },
        "BoxExtent": {
          "X": 249.78352,
          "Y": 219.49094,
          "Z": 114.966965
        },
        "SphereRadius": 268.68152
      },
      "bLODsShareStaticLighting": false,
      "ScreenSize": [
        1.0,
        0.6,
        0.2,
        0.0,
        0.0,
        0.0,
        0.0,
        0.0
      ]
    }
  }
]