[
  {
    "Type": "WeaponGunDataAsset",
    "Name": "WeapMG3_WeaponGunData",
    "Class": "UScriptClass'WeaponGunDataAsset'",
    "Properties": {
      "WeaponGunConfig": {
        "AmmoItemID": "Item_Ammo_762mm_C",
        "TracerClass": {
          "ObjectName": "ParticleSystem'P_Tracer_LMG'",
          "ObjectPath": "TslGame/Content/Export_Marek/Tracer/P_Tracer_LMG.10"
        },
        "TracerAmmoMod": 5,
        "TracerAmmoMin": 10,
        "AmmoPerClip": 75,
        "TimeBetweenShots": 0.085714,
        "AttachmentTagData": [
          {
            "AttachmentSlotID": "EWeaponAttachmentSlotID::UpperRail",
            "AttachableTags": [
              "UpperSmall",
              "UpperReddot",
              "UpperHolo"
            ]
          }
        ],
        "TimeBetweenShotsOverride": [
          {
            "EFiringMode::FullAutoFast": 0.060606
          },
          {
            "EFiringMode::FullAuto": 0.090909
          }
        ],
        "NoAnimReloadDuration": 3.5,
        "FiringModes": [
          "EFiringMode::FullAuto",
          "EFiringMode::FullAutoFast"
        ],
        "BurstShots": 1,
        "FiringBulletsSpread": 1.0,
        "WeaponLength": 67.0,
        "ShoulderLength": 22.0,
        "HandWeaponOffset": {
          "X": 3.0,
          "Y": 0.0,
          "Z": -3.0
        },
        "HandWeaponOffsetFPP": {
          "X": 3.0,
          "Y": -0.5,
          "Z": 2.0
        },
        "ADSTimeMultiplier": 0.9,
        "GunshotFiremodeMap": [
          {
            "EFiringMode::FullAutoFast": {
              "ObjectName": "AkAudioEvent'Weapon_MG3_Fire_LongTail_Fast'",
              "ObjectPath": "TslGame/Content/WwiseAssets/Weapons/MG3/Weapon_MG3_Fire_LongTail_Fast.0"
            }
          },
          {
            "EFiringMode::FullAuto": {
              "ObjectName": "AkAudioEvent'Weapon_MG3_Fire_LongTail_Slow'",
              "ObjectPath": "TslGame/Content/WwiseAssets/Weapons/MG3/Weapon_MG3_Fire_LongTail_Slow.0"
            }
          }
        ]
      },
      "WeaponDeviationConfig": {
        "DeviationBase": 3.1,
        "DeviationBaseAim": 1.1,
        "MOA": 3.0,
        "DeviationRecoilGain": 1.3,
        "DeviationRecoilGainADS": 0.12,
        "DeviationMax": 10.0,
        "DeviationMaxMove": 3.2,
        "DeviationMoveMaxReferenceVelocity": 300.0,
        "DeviationStanceProne": 0.7
      },
      "WeaponAnimConfig": {
        "CharacterGripBlendspace": {
          "ObjectName": "BlendSpace1D'Weapon_MG3_Grip_RD'",
          "ObjectPath": "TslGame/Content/Animations/Battlegrounds/Anims/WeaponOperation/MG3/Redux/Weapon_MG3_Grip_RD.0"
        },
        "CharacterReloadTactical": {
          "ObjectName": "AnimMontage'CharacterWeapon_MG3_Reload_Montage_RD'",
          "ObjectPath": "TslGame/Content/Animations/Battlegrounds/Anims/WeaponOperation/MG3/Redux/CharacterWeapon_MG3_Reload_Montage_RD.0"
        },
        "CharacterReloadCharge": {
          "ObjectName": "AnimMontage'CharacterWeapon_MG3_Reload_Charge_Montage_RD'",
          "ObjectPath": "TslGame/Content/Animations/Battlegrounds/Anims/WeaponOperation/MG3/Redux/CharacterWeapon_MG3_Reload_Charge_Montage_RD.0"
        },
        "WeaponInspectMontage": {
          "ObjectName": "AnimMontage'Rifle_Combat_FPP_Inspect_Montage'",
          "ObjectPath": "TslGame/Content/Animations/Battlegrounds/Anims/Rifle/Idling/Rifle_Combat_FPP_Inspect_Montage.0"
        },
        "LobbyAnimClassOverride": "EWeaponClass::Class_Rifle",
        "bUseLobbyAnimClassOverride": true,
        "ReloadDurationTactical": 7.1,
        "ReloadDurationCharge": 8.2,
        "ReloadDurationMagOut": 0.4,
        "ShotCameraShake": {
          "ObjectName": "BlueprintGeneratedClass'CS_WeapGun_LMG_MG3_C'",
          "ObjectPath": "TslGame/Content/Blueprints/Weapons/WeaponConfig/CS_WeapGun_LMG_MG3.0"
        },
        "ShotCameraShakeIronsight": {
          "ObjectName": "BlueprintGeneratedClass'CS_WeapGun_LMG_MG3_Ironsight_C'",
          "ObjectPath": "TslGame/Content/Blueprints/Weapons/WeaponConfig/CS_WeapGun_LMG_MG3_Ironsight.0"
        },
        "ShotCameraShakeADS": {
          "ObjectName": "BlueprintGeneratedClass'CS_WeapGun_LMG_MG3_ADS_C'",
          "ObjectPath": "TslGame/Content/Blueprints/Weapons/WeaponConfig/CS_WeapGun_LMG_MG3_ADS.0"
        },
        "RecoilKickADS": 0.85,
        "RecoilKick_MovementMaxMultiplier": 1.3,
        "ShakeScaleStanceMap": [
          {
            "EAnimStance::Crouch": 0.7
          },
          {
            "EAnimStance::Prone": 0.35
          }
        ],
        "ADSAnimRecoilStanceMap": [
          {
            "EAnimStance::Prone": 0.85
          }
        ]
      },
      "ConsoleWeaponRecoilData": {
        "ObjectName": "WeaponGunRecoilData'WeapM249_RecoilDataConsole'",
        "ObjectPath": "TslGame/Content/Blueprints/Weapons/DataAssets/WeapM249_RecoilDataConsole.0"
      }
    }
  }
]